{
  "config": {
    "model": "baseline",
    "dataset": "synthetic_OC",
    "epochs": 15,
    "batch_size": 32,
    "lr": 0.001,
    "n_folds": 5,
    "no_cv": false,
    "seed": 42,
    "device": null
  },
  "cv_summary": {
    "categorical_accuracy": {
      "mean": 0.6739989042282104,
      "std": 0.05488125343854227,
      "values": [
        0.7129237055778503,
        0.7238888740539551,
        0.589211642742157,
        0.7159090638160706,
        0.6280612349510193
      ]
    },
    "quadratic_weighted_kappa": {
      "mean": 0.5109021878210843,
      "std": 0.16462974366891073,
      "values": [
        0.6296471045806746,
        0.6352619698229772,
        0.26254271441932486,
        0.662279058350403,
        0.36478009193204175
      ]
    },
    "ordinal_accuracy": {
      "mean": 0.8130839347839356,
      "std": 0.053330969666498626,
      "values": [
        0.8469279408454895,
        0.8611111044883728,
        0.7437759041786194,
        0.8610537052154541,
        0.7525510191917419
      ]
    },
    "mean_absolute_error": {
      "mean": 0.6063958644866944,
      "std": 0.14459662960366884,
      "values": [
        0.4994703531265259,
        0.4811111092567444,
        0.8132780194282532,
        0.48811984062194824,
        0.75
      ]
    }
  },
  "fold_results": [
    {
      "fold": 1,
      "metrics": {
        "categorical_accuracy": 0.7129237055778503,
        "ordinal_accuracy": 0.8469279408454895,
        "quadratic_weighted_kappa": 0.6296471045806746,
        "mean_absolute_error": 0.4994703531265259,
        "train_accuracy": 0.7124485596707819,
        "train_loss": 1.0194133281707765,
        "best_epoch": 15,
        "total_epochs": 15,
        "parameters": 134055,
        "model_type": "BaselineGPCM"
      },
      "training_history": [
        {
          "epoch": 1,
          "train_loss": 1.274004077911377,
          "train_accuracy": 0.5857105809128631,
          "test_accuracy": 0.6276482939720154,
          "qwk": 0.07108418592908372,
          "ordinal_accuracy": 0.7420550584793091,
          "mae": 0.7759534120559692,
          "gradient_norm": 0.7954570353031158,
          "learning_rate": 0.001
        },
        {
          "epoch": 2,
          "train_loss": 1.141758918762207,
          "train_accuracy": 0.6038602941176471,
          "test_accuracy": 0.6271186470985413,
          "qwk": 0.030925154739804506,
          "ordinal_accuracy": 0.7383474707603455,
          "mae": 0.7844279408454895,
          "gradient_norm": 0.16551880538463593,
          "learning_rate": 0.001
        },
        {
          "epoch": 3,
          "train_loss": 1.1243970394134521,
          "train_accuracy": 0.6107954545454546,
          "test_accuracy": 0.6281779408454895,
          "qwk": 0.03356208986625253,
          "ordinal_accuracy": 0.7378178238868713,
          "mae": 0.7833686470985413,
          "gradient_norm": 0.054127972573041916,
          "learning_rate": 0.001
        },
        {
          "epoch": 4,
          "train_loss": 1.1245898723602294,
          "train_accuracy": 0.6099585062240664,
          "test_accuracy": 0.6308262944221497,
          "qwk": 0.05231672790166175,
          "ordinal_accuracy": 0.7409957647323608,
          "mae": 0.7754237055778503,
          "gradient_norm": 0.0581768162548542,
          "learning_rate": 0.001
        },
        {
          "epoch": 5,
          "train_loss": 1.1211106061935425,
          "train_accuracy": 0.610546875,
          "test_accuracy": 0.633474588394165,
          "qwk": 0.09873126359064033,
          "ordinal_accuracy": 0.7494703531265259,
          "mae": 0.7590042352676392,
          "gradient_norm": 0.07078969553112983,
          "learning_rate": 0.001
        },
        {
          "epoch": 6,
          "train_loss": 1.108652114868164,
          "train_accuracy": 0.6203512396694215,
          "test_accuracy": 0.6393008232116699,
          "qwk": 0.20296592836838645,
          "ordinal_accuracy": 0.7595338821411133,
          "mae": 0.7293432354927063,
          "gradient_norm": 0.0862475425004959,
          "learning_rate": 0.001
        },
        {
          "epoch": 7,
          "train_loss": 1.0867730617523192,
          "train_accuracy": 0.641265368852459,
          "test_accuracy": 0.6652542352676392,
          "qwk": 0.45280997763143793,
          "ordinal_accuracy": 0.7955508232116699,
          "mae": 0.6387711763381958,
          "gradient_norm": 0.09452915862202645,
          "learning_rate": 0.001
        },
        {
          "epoch": 8,
          "train_loss": 1.0795897722244263,
          "train_accuracy": 0.6624740663900415,
          "test_accuracy": 0.6784957647323608,
          "qwk": 0.5497268519783667,
          "ordinal_accuracy": 0.8183262944221497,
          "mae": 0.5942796468734741,
          "gradient_norm": 0.13752977401018143,
          "learning_rate": 0.001
        },
        {
          "epoch": 9,
          "train_loss": 1.065497922897339,
          "train_accuracy": 0.6754907024793388,
          "test_accuracy": 0.6869703531265259,
          "qwk": 0.5383218719685898,
          "ordinal_accuracy": 0.819915235042572,
          "mae": 0.5789194703102112,
          "gradient_norm": 0.13271243572235109,
          "learning_rate": 0.001
        },
        {
          "epoch": 10,
          "train_loss": 1.053440546989441,
          "train_accuracy": 0.6810165975103735,
          "test_accuracy": 0.7002118825912476,
          "qwk": 0.5781666159865801,
          "ordinal_accuracy": 0.8326271176338196,
          "mae": 0.5418432354927063,
          "gradient_norm": 0.09532445967197418,
          "learning_rate": 0.001
        },
        {
          "epoch": 11,
          "train_loss": 1.040123748779297,
          "train_accuracy": 0.6962809917355371,
          "test_accuracy": 0.6996821761131287,
          "qwk": 0.6029923430321593,
          "ordinal_accuracy": 0.8358050584793091,
          "mae": 0.538665235042572,
          "gradient_norm": 0.0678770586848259,
          "learning_rate": 0.001
        },
        {
          "epoch": 12,
          "train_loss": 1.0334376335144042,
          "train_accuracy": 0.7022210743801653,
          "test_accuracy": 0.7086864113807678,
          "qwk": 0.6030443760153702,
          "ordinal_accuracy": 0.8395127058029175,
          "mae": 0.5206567645072937,
          "gradient_norm": 0.08795336037874221,
          "learning_rate": 0.001
        },
        {
          "epoch": 13,
          "train_loss": 1.0265593647956848,
          "train_accuracy": 0.7056327160493827,
          "test_accuracy": 0.711334764957428,
          "qwk": 0.612375282877271,
          "ordinal_accuracy": 0.8432203531265259,
          "mae": 0.5105932354927063,
          "gradient_norm": 0.058276920765638354,
          "learning_rate": 0.001
        },
        {
          "epoch": 14,
          "train_loss": 1.0249314785003663,
          "train_accuracy": 0.7083765560165975,
          "test_accuracy": 0.7097457647323608,
          "qwk": 0.6286321608994487,
          "ordinal_accuracy": 0.8458686470985413,
          "mae": 0.508474588394165,
          "gradient_norm": 0.06725867986679077,
          "learning_rate": 0.001
        },
        {
          "epoch": 15,
          "train_loss": 1.0194133281707765,
          "train_accuracy": 0.7124485596707819,
          "test_accuracy": 0.7129237055778503,
          "qwk": 0.6296471045806746,
          "ordinal_accuracy": 0.8469279408454895,
          "mae": 0.4994703531265259,
          "gradient_norm": 0.049483422935009,
          "learning_rate": 0.001
        }
      ]
    },
    {
      "fold": 2,
      "metrics": {
        "categorical_accuracy": 0.7238888740539551,
        "ordinal_accuracy": 0.8611111044883728,
        "quadratic_weighted_kappa": 0.6352619698229772,
        "mean_absolute_error": 0.4811111092567444,
        "train_accuracy": 0.7004668049792531,
        "train_loss": 1.0346227884292603,
        "best_epoch": 15,
        "total_epochs": 15,
        "parameters": 134055,
        "model_type": "BaselineGPCM"
      },
      "training_history": [
        {
          "epoch": 1,
          "train_loss": 1.2875203847885133,
          "train_accuracy": 0.509375,
          "test_accuracy": 0.6388888955116272,
          "qwk": 0.03293554996261849,
          "ordinal_accuracy": 0.7483333349227905,
          "mae": 0.7661111354827881,
          "gradient_norm": 0.8197951495647431,
          "learning_rate": 0.001
        },
        {
          "epoch": 2,
          "train_loss": 1.1501159429550172,
          "train_accuracy": 0.6021090534979424,
          "test_accuracy": 0.6377778053283691,
          "qwk": 0.0025097764547947765,
          "ordinal_accuracy": 0.7461110949516296,
          "mae": 0.7711111307144165,
          "gradient_norm": 0.19093738049268721,
          "learning_rate": 0.001
        },
        {
          "epoch": 3,
          "train_loss": 1.1361330509185792,
          "train_accuracy": 0.599948347107438,
          "test_accuracy": 0.6388888955116272,
          "qwk": 0.0026941575936089146,
          "ordinal_accuracy": 0.746666669845581,
          "mae": 0.769444465637207,
          "gradient_norm": 0.03319165296852589,
          "learning_rate": 0.001
        },
        {
          "epoch": 4,
          "train_loss": 1.134607982635498,
          "train_accuracy": 0.6018518518518519,
          "test_accuracy": 0.6377778053283691,
          "qwk": 0.0016086165897327698,
          "ordinal_accuracy": 0.745555579662323,
          "mae": 0.7722222208976746,
          "gradient_norm": 0.031192367523908617,
          "learning_rate": 0.001
        },
        {
          "epoch": 5,
          "train_loss": 1.1341632604599,
          "train_accuracy": 0.602366255144033,
          "test_accuracy": 0.6388888955116272,
          "qwk": 0.014354066985646008,
          "ordinal_accuracy": 0.7483333349227905,
          "mae": 0.7672222256660461,
          "gradient_norm": 0.034348152577877045,
          "learning_rate": 0.0008
        },
        {
          "epoch": 6,
          "train_loss": 1.1355940341949462,
          "train_accuracy": 0.5990663900414938,
          "test_accuracy": 0.6377778053283691,
          "qwk": 0.018757266054727495,
          "ordinal_accuracy": 0.7488889098167419,
          "mae": 0.7672222256660461,
          "gradient_norm": 0.03852040991187096,
          "learning_rate": 0.0008
        },
        {
          "epoch": 7,
          "train_loss": 1.1332678318023681,
          "train_accuracy": 0.5997147302904564,
          "test_accuracy": 0.6405555605888367,
          "qwk": 0.05119353153603312,
          "ordinal_accuracy": 0.7527777552604675,
          "mae": 0.757777750492096,
          "gradient_norm": 0.045526675134897235,
          "learning_rate": 0.0008
        },
        {
          "epoch": 8,
          "train_loss": 1.1271171808242797,
          "train_accuracy": 0.6025309917355371,
          "test_accuracy": 0.644444465637207,
          "qwk": 0.09815540581624804,
          "ordinal_accuracy": 0.757777750492096,
          "mae": 0.7438889145851135,
          "gradient_norm": 0.05867109075188637,
          "learning_rate": 0.0008
        },
        {
          "epoch": 9,
          "train_loss": 1.1204823493957519,
          "train_accuracy": 0.6038641078838174,
          "test_accuracy": 0.6538888812065125,
          "qwk": 0.2220406589056807,
          "ordinal_accuracy": 0.7716666460037231,
          "mae": 0.7088888883590698,
          "gradient_norm": 0.07834233045578003,
          "learning_rate": 0.0008
        },
        {
          "epoch": 10,
          "train_loss": 1.1024649620056153,
          "train_accuracy": 0.6300361570247934,
          "test_accuracy": 0.6911110877990723,
          "qwk": 0.4857062953168634,
          "ordinal_accuracy": 0.8111110925674438,
          "mae": 0.6005555391311646,
          "gradient_norm": 0.10618613064289092,
          "learning_rate": 0.0008
        },
        {
          "epoch": 11,
          "train_loss": 1.0853249073028564,
          "train_accuracy": 0.6652520576131687,
          "test_accuracy": 0.7005555629730225,
          "qwk": 0.5648524808323377,
          "ordinal_accuracy": 0.8216666579246521,
          "mae": 0.5666666626930237,
          "gradient_norm": 0.14450693577528,
          "learning_rate": 0.0008
        },
        {
          "epoch": 12,
          "train_loss": 1.0714327335357665,
          "train_accuracy": 0.6747159090909091,
          "test_accuracy": 0.7072222232818604,
          "qwk": 0.5796430163375259,
          "ordinal_accuracy": 0.8338888883590698,
          "mae": 0.5416666865348816,
          "gradient_norm": 0.16341663300991058,
          "learning_rate": 0.0008
        },
        {
          "epoch": 13,
          "train_loss": 1.0507023096084596,
          "train_accuracy": 0.6860911885245902,
          "test_accuracy": 0.7111111283302307,
          "qwk": 0.5941940340641761,
          "ordinal_accuracy": 0.8416666388511658,
          "mae": 0.5244444608688354,
          "gradient_norm": 0.09873843491077423,
          "learning_rate": 0.0008
        },
        {
          "epoch": 14,
          "train_loss": 1.0414954662322997,
          "train_accuracy": 0.6942148760330579,
          "test_accuracy": 0.7188888788223267,
          "qwk": 0.6349426608539808,
          "ordinal_accuracy": 0.8527777791023254,
          "mae": 0.4983333349227905,
          "gradient_norm": 0.11862856522202492,
          "learning_rate": 0.0008
        },
        {
          "epoch": 15,
          "train_loss": 1.0346227884292603,
          "train_accuracy": 0.7004668049792531,
          "test_accuracy": 0.7238888740539551,
          "qwk": 0.6352619698229772,
          "ordinal_accuracy": 0.8611111044883728,
          "mae": 0.4811111092567444,
          "gradient_norm": 0.08562540411949157,
          "learning_rate": 0.0008
        }
      ]
    },
    {
      "fold": 3,
      "metrics": {
        "categorical_accuracy": 0.589211642742157,
        "ordinal_accuracy": 0.7437759041786194,
        "quadratic_weighted_kappa": 0.26254271441932486,
        "mean_absolute_error": 0.8132780194282532,
        "train_accuracy": 0.6409465020576132,
        "train_loss": 1.0881969451904296,
        "best_epoch": 15,
        "total_epochs": 15,
        "parameters": 134055,
        "model_type": "BaselineGPCM"
      },
      "training_history": [
        {
          "epoch": 1,
          "train_loss": 1.2910691499710083,
          "train_accuracy": 0.5002593360995851,
          "test_accuracy": 0.5529045462608337,
          "qwk": 0.002748020581079591,
          "ordinal_accuracy": 0.6887966990470886,
          "mae": 0.9398339986801147,
          "gradient_norm": 0.8028642892837524,
          "learning_rate": 0.001
        },
        {
          "epoch": 2,
          "train_loss": 1.1370460510253906,
          "train_accuracy": 0.6238378099173554,
          "test_accuracy": 0.5580912828445435,
          "qwk": 0.0,
          "ordinal_accuracy": 0.6929460763931274,
          "mae": 0.9294605851173401,
          "gradient_norm": 0.2121556043624878,
          "learning_rate": 0.001
        },
        {
          "epoch": 3,
          "train_loss": 1.1181551694869996,
          "train_accuracy": 0.6239626556016598,
          "test_accuracy": 0.5580912828445435,
          "qwk": 0.0,
          "ordinal_accuracy": 0.6929460763931274,
          "mae": 0.9294605851173401,
          "gradient_norm": 0.033447226881980895,
          "learning_rate": 0.001
        },
        {
          "epoch": 4,
          "train_loss": 1.116749930381775,
          "train_accuracy": 0.6239626556016598,
          "test_accuracy": 0.5580912828445435,
          "qwk": 0.0,
          "ordinal_accuracy": 0.6929460763931274,
          "mae": 0.9294605851173401,
          "gradient_norm": 0.017456384561955928,
          "learning_rate": 0.001
        },
        {
          "epoch": 5,
          "train_loss": 1.1170268297195434,
          "train_accuracy": 0.6239626556016598,
          "test_accuracy": 0.5580912828445435,
          "qwk": 0.0,
          "ordinal_accuracy": 0.6929460763931274,
          "mae": 0.9294605851173401,
          "gradient_norm": 0.016859490610659122,
          "learning_rate": 0.0008
        },
        {
          "epoch": 6,
          "train_loss": 1.1181055307388306,
          "train_accuracy": 0.6223958333333334,
          "test_accuracy": 0.5580912828445435,
          "qwk": 0.0,
          "ordinal_accuracy": 0.6929460763931274,
          "mae": 0.9294605851173401,
          "gradient_norm": 0.015999259240925313,
          "learning_rate": 0.0008
        },
        {
          "epoch": 7,
          "train_loss": 1.1213968753814698,
          "train_accuracy": 0.6192226890756303,
          "test_accuracy": 0.5570539236068726,
          "qwk": -0.0017020888581567029,
          "ordinal_accuracy": 0.6919087171554565,
          "mae": 0.9315352439880371,
          "gradient_norm": 0.017364857718348503,
          "learning_rate": 0.0008
        },
        {
          "epoch": 8,
          "train_loss": 1.1143317461013793,
          "train_accuracy": 0.6256456611570248,
          "test_accuracy": 0.5570539236068726,
          "qwk": -0.0017020888581567029,
          "ordinal_accuracy": 0.6919087171554565,
          "mae": 0.9315352439880371,
          "gradient_norm": 0.01847163587808609,
          "learning_rate": 0.0008
        },
        {
          "epoch": 9,
          "train_loss": 1.1146814107894898,
          "train_accuracy": 0.6238329875518672,
          "test_accuracy": 0.5570539236068726,
          "qwk": -0.0025494670589507606,
          "ordinal_accuracy": 0.6919087171554565,
          "mae": 0.932572603225708,
          "gradient_norm": 0.02239828370511532,
          "learning_rate": 0.00064
        },
        {
          "epoch": 10,
          "train_loss": 1.1146915435791016,
          "train_accuracy": 0.6227864583333333,
          "test_accuracy": 0.5570539236068726,
          "qwk": -0.001962167142516069,
          "ordinal_accuracy": 0.6919087171554565,
          "mae": 0.932572603225708,
          "gradient_norm": 0.025474533997476102,
          "learning_rate": 0.00064
        },
        {
          "epoch": 11,
          "train_loss": 1.1118153572082519,
          "train_accuracy": 0.6247406639004149,
          "test_accuracy": 0.5570539236068726,
          "qwk": 0.0023711278753237863,
          "ordinal_accuracy": 0.6929460763931274,
          "mae": 0.9310166239738464,
          "gradient_norm": 0.029743052646517755,
          "learning_rate": 0.00064
        },
        {
          "epoch": 12,
          "train_loss": 1.1241248369216919,
          "train_accuracy": 0.61306330472103,
          "test_accuracy": 0.5596473217010498,
          "qwk": 0.0185483354009629,
          "ordinal_accuracy": 0.6955394148826599,
          "mae": 0.9221991896629333,
          "gradient_norm": 0.03971065655350685,
          "learning_rate": 0.00064
        },
        {
          "epoch": 13,
          "train_loss": 1.1054242134094239,
          "train_accuracy": 0.6297778925619835,
          "test_accuracy": 0.5591286420822144,
          "qwk": 0.03234481268762879,
          "ordinal_accuracy": 0.6970954537391663,
          "mae": 0.9211618304252625,
          "gradient_norm": 0.045178625732660294,
          "learning_rate": 0.00064
        },
        {
          "epoch": 14,
          "train_loss": 1.1008808851242065,
          "train_accuracy": 0.6308350622406639,
          "test_accuracy": 0.5663900375366211,
          "qwk": 0.10131969584135703,
          "ordinal_accuracy": 0.7121369242668152,
          "mae": 0.8884854912757874,
          "gradient_norm": 0.06067131906747818,
          "learning_rate": 0.00064
        },
        {
          "epoch": 15,
          "train_loss": 1.0881969451904296,
          "train_accuracy": 0.6409465020576132,
          "test_accuracy": 0.589211642742157,
          "qwk": 0.26254271441932486,
          "ordinal_accuracy": 0.7437759041786194,
          "mae": 0.8132780194282532,
          "gradient_norm": 0.0810165598988533,
          "learning_rate": 0.00064
        }
      ]
    },
    {
      "fold": 4,
      "metrics": {
        "categorical_accuracy": 0.7159090638160706,
        "ordinal_accuracy": 0.8610537052154541,
        "quadratic_weighted_kappa": 0.662279058350403,
        "mean_absolute_error": 0.48811984062194824,
        "train_accuracy": 0.711689330543933,
        "train_loss": 1.021038866043091,
        "best_epoch": 14,
        "total_epochs": 15,
        "parameters": 134055,
        "model_type": "BaselineGPCM"
      },
      "training_history": [
        {
          "epoch": 1,
          "train_loss": 1.174534225463867,
          "train_accuracy": 0.6213692946058091,
          "test_accuracy": 0.620351254940033,
          "qwk": 0.11532123291097918,
          "ordinal_accuracy": 0.7396694421768188,
          "mae": 0.7815082669258118,
          "gradient_norm": 0.6595146745443344,
          "learning_rate": 0.001
        },
        {
          "epoch": 2,
          "train_loss": 1.1179832220077515,
          "train_accuracy": 0.6166666666666667,
          "test_accuracy": 0.6188016533851624,
          "qwk": 0.07087426771325,
          "ordinal_accuracy": 0.7308884263038635,
          "mae": 0.8042355179786682,
          "gradient_norm": 0.11160665899515151,
          "learning_rate": 0.001
        },
        {
          "epoch": 3,
          "train_loss": 1.1161135911941529,
          "train_accuracy": 0.6156381856540084,
          "test_accuracy": 0.62861567735672,
          "qwk": 0.14983002248264932,
          "ordinal_accuracy": 0.745351254940033,
          "mae": 0.7665289044380188,
          "gradient_norm": 0.10286391228437423,
          "learning_rate": 0.001
        },
        {
          "epoch": 4,
          "train_loss": 1.1020900011062622,
          "train_accuracy": 0.6310911016949152,
          "test_accuracy": 0.6585744023323059,
          "qwk": 0.3388627575092855,
          "ordinal_accuracy": 0.7825413346290588,
          "mae": 0.6704545617103577,
          "gradient_norm": 0.143362557888031,
          "learning_rate": 0.001
        },
        {
          "epoch": 5,
          "train_loss": 1.0650364398956298,
          "train_accuracy": 0.6748971193415638,
          "test_accuracy": 0.6869834661483765,
          "qwk": 0.5490116395301046,
          "ordinal_accuracy": 0.8290289044380188,
          "mae": 0.5686983466148376,
          "gradient_norm": 0.10432544946670533,
          "learning_rate": 0.001
        },
        {
          "epoch": 6,
          "train_loss": 1.0583552360534667,
          "train_accuracy": 0.6922778925619835,
          "test_accuracy": 0.6993801593780518,
          "qwk": 0.5861653442493676,
          "ordinal_accuracy": 0.8383264541625977,
          "mae": 0.5444214940071106,
          "gradient_norm": 0.19759079515933992,
          "learning_rate": 0.001
        },
        {
          "epoch": 7,
          "train_loss": 1.0442160367965698,
          "train_accuracy": 0.6983471074380165,
          "test_accuracy": 0.6962810158729553,
          "qwk": 0.5608085634057984,
          "ordinal_accuracy": 0.8347107172012329,
          "mae": 0.547520637512207,
          "gradient_norm": 0.11089973449707032,
          "learning_rate": 0.001
        },
        {
          "epoch": 8,
          "train_loss": 1.0372934103012086,
          "train_accuracy": 0.6943724066390041,
          "test_accuracy": 0.7040289044380188,
          "qwk": 0.5901005826821997,
          "ordinal_accuracy": 0.8429751992225647,
          "mae": 0.5289255976676941,
          "gradient_norm": 0.11012951210141182,
          "learning_rate": 0.001
        },
        {
          "epoch": 9,
          "train_loss": 1.0301628351211547,
          "train_accuracy": 0.7034491701244814,
          "test_accuracy": 0.6978305578231812,
          "qwk": 0.620102321670559,
          "ordinal_accuracy": 0.8409090638160706,
          "mae": 0.5402892827987671,
          "gradient_norm": 0.09711156263947487,
          "learning_rate": 0.001
        },
        {
          "epoch": 10,
          "train_loss": 1.0277194499969482,
          "train_accuracy": 0.7078125,
          "test_accuracy": 0.7128099203109741,
          "qwk": 0.6263928657478706,
          "ordinal_accuracy": 0.8574380278587341,
          "mae": 0.49793389439582825,
          "gradient_norm": 0.138207845389843,
          "learning_rate": 0.001
        },
        {
          "epoch": 11,
          "train_loss": 1.0228780508041382,
          "train_accuracy": 0.7126556016597511,
          "test_accuracy": 0.7128099203109741,
          "qwk": 0.646693245525864,
          "ordinal_accuracy": 0.8595041036605835,
          "mae": 0.4958677589893341,
          "gradient_norm": 0.07359704077243805,
          "learning_rate": 0.001
        },
        {
          "epoch": 12,
          "train_loss": 1.0197057723999023,
          "train_accuracy": 0.7126807851239669,
          "test_accuracy": 0.7133264541625977,
          "qwk": 0.6504428734437132,
          "ordinal_accuracy": 0.8584710955619812,
          "mae": 0.49793389439582825,
          "gradient_norm": 0.05458995029330253,
          "learning_rate": 0.001
        },
        {
          "epoch": 13,
          "train_loss": 1.0201037406921387,
          "train_accuracy": 0.7129149377593361,
          "test_accuracy": 0.7174586653709412,
          "qwk": 0.6572449150447699,
          "ordinal_accuracy": 0.8636363744735718,
          "mae": 0.48243802785873413,
          "gradient_norm": 0.0793969988822937,
          "learning_rate": 0.001
        },
        {
          "epoch": 14,
          "train_loss": 1.021038866043091,
          "train_accuracy": 0.711689330543933,
          "test_accuracy": 0.7159090638160706,
          "qwk": 0.662279058350403,
          "ordinal_accuracy": 0.8610537052154541,
          "mae": 0.48811984062194824,
          "gradient_norm": 0.047087249159812924,
          "learning_rate": 0.001
        },
        {
          "epoch": 15,
          "train_loss": 1.0170997619628905,
          "train_accuracy": 0.7153925619834711,
          "test_accuracy": 0.7174586653709412,
          "qwk": 0.6560370436679328,
          "ordinal_accuracy": 0.8636363744735718,
          "mae": 0.4819214940071106,
          "gradient_norm": 0.08164443150162697,
          "learning_rate": 0.001
        }
      ]
    },
    {
      "fold": 5,
      "metrics": {
        "categorical_accuracy": 0.6280612349510193,
        "ordinal_accuracy": 0.7525510191917419,
        "quadratic_weighted_kappa": 0.36478009193204175,
        "mean_absolute_error": 0.75,
        "train_accuracy": 0.6490585774058577,
        "train_loss": 1.0908618450164795,
        "best_epoch": 15,
        "total_epochs": 15,
        "parameters": 134055,
        "model_type": "BaselineGPCM"
      },
      "training_history": [
        {
          "epoch": 1,
          "train_loss": 1.340744185447693,
          "train_accuracy": 0.42486979166666666,
          "test_accuracy": 0.5959183573722839,
          "qwk": 0.020331225870070746,
          "ordinal_accuracy": 0.7153061032295227,
          "mae": 0.8581632375717163,
          "gradient_norm": 0.948985505104065,
          "learning_rate": 0.001
        },
        {
          "epoch": 2,
          "train_loss": 1.156467342376709,
          "train_accuracy": 0.6049679487179487,
          "test_accuracy": 0.5969387888908386,
          "qwk": 0.0,
          "ordinal_accuracy": 0.7117347121238708,
          "mae": 0.8647959232330322,
          "gradient_norm": 0.25305181443691255,
          "learning_rate": 0.001
        },
        {
          "epoch": 3,
          "train_loss": 1.1284744501113892,
          "train_accuracy": 0.6110819327731093,
          "test_accuracy": 0.5969387888908386,
          "qwk": 0.0,
          "ordinal_accuracy": 0.7117347121238708,
          "mae": 0.8647959232330322,
          "gradient_norm": 0.030988175980746747,
          "learning_rate": 0.001
        },
        {
          "epoch": 4,
          "train_loss": 1.1269325256347655,
          "train_accuracy": 0.6127092050209205,
          "test_accuracy": 0.5969387888908386,
          "qwk": 0.0,
          "ordinal_accuracy": 0.7117347121238708,
          "mae": 0.8647959232330322,
          "gradient_norm": 0.02004130817949772,
          "learning_rate": 0.001
        },
        {
          "epoch": 5,
          "train_loss": 1.1258824348449707,
          "train_accuracy": 0.6143229166666667,
          "test_accuracy": 0.5969387888908386,
          "qwk": 0.0,
          "ordinal_accuracy": 0.7117347121238708,
          "mae": 0.8647959232330322,
          "gradient_norm": 0.018944518454372884,
          "learning_rate": 0.0008
        },
        {
          "epoch": 6,
          "train_loss": 1.1236572265625,
          "train_accuracy": 0.6159232365145229,
          "test_accuracy": 0.5969387888908386,
          "qwk": 0.0,
          "ordinal_accuracy": 0.7117347121238708,
          "mae": 0.8647959232330322,
          "gradient_norm": 0.019673540070652962,
          "learning_rate": 0.0008
        },
        {
          "epoch": 7,
          "train_loss": 1.1237789869308472,
          "train_accuracy": 0.6160529045643154,
          "test_accuracy": 0.597449004650116,
          "qwk": 0.004869294991738493,
          "ordinal_accuracy": 0.7122448682785034,
          "mae": 0.863265335559845,
          "gradient_norm": 0.020845048874616624,
          "learning_rate": 0.0008
        },
        {
          "epoch": 8,
          "train_loss": 1.125808310508728,
          "train_accuracy": 0.6129707112970711,
          "test_accuracy": 0.597449004650116,
          "qwk": 0.004869294991738493,
          "ordinal_accuracy": 0.7122448682785034,
          "mae": 0.863265335559845,
          "gradient_norm": 0.024701220355927943,
          "learning_rate": 0.0008
        },
        {
          "epoch": 9,
          "train_loss": 1.1303874731063843,
          "train_accuracy": 0.606781914893617,
          "test_accuracy": 0.597449004650116,
          "qwk": 0.013143252574956077,
          "ordinal_accuracy": 0.7132652997970581,
          "mae": 0.859183669090271,
          "gradient_norm": 0.028319262713193894,
          "learning_rate": 0.00064
        },
        {
          "epoch": 10,
          "train_loss": 1.1310236215591432,
          "train_accuracy": 0.6053685897435898,
          "test_accuracy": 0.5979591608047485,
          "qwk": 0.023118314802274775,
          "ordinal_accuracy": 0.7153061032295227,
          "mae": 0.8545918464660645,
          "gradient_norm": 0.03297848030924797,
          "learning_rate": 0.00064
        },
        {
          "epoch": 11,
          "train_loss": 1.118269681930542,
          "train_accuracy": 0.6178682572614108,
          "test_accuracy": 0.6000000238418579,
          "qwk": 0.050017288741187715,
          "ordinal_accuracy": 0.7188775539398193,
          "mae": 0.8443877696990967,
          "gradient_norm": 0.038892324268817904,
          "learning_rate": 0.00064
        },
        {
          "epoch": 12,
          "train_loss": 1.1152016639709472,
          "train_accuracy": 0.6195539419087137,
          "test_accuracy": 0.6020408272743225,
          "qwk": 0.07281235764277127,
          "ordinal_accuracy": 0.7214285731315613,
          "mae": 0.8377550840377808,
          "gradient_norm": 0.04805544540286064,
          "learning_rate": 0.00064
        },
        {
          "epoch": 13,
          "train_loss": 1.1093156576156615,
          "train_accuracy": 0.6235736514522822,
          "test_accuracy": 0.6071428656578064,
          "qwk": 0.10339778906800312,
          "ordinal_accuracy": 0.7239795923233032,
          "mae": 0.8295918107032776,
          "gradient_norm": 0.06609546542167663,
          "learning_rate": 0.00064
        },
        {
          "epoch": 14,
          "train_loss": 1.0995678663253785,
          "train_accuracy": 0.633298755186722,
          "test_accuracy": 0.6147959232330322,
          "qwk": 0.20350417280524125,
          "ordinal_accuracy": 0.7336734533309937,
          "mae": 0.8025510311126709,
          "gradient_norm": 0.07931799292564393,
          "learning_rate": 0.00064
        },
        {
          "epoch": 15,
          "train_loss": 1.0908618450164795,
          "train_accuracy": 0.6490585774058577,
          "test_accuracy": 0.6280612349510193,
          "qwk": 0.36478009193204175,
          "ordinal_accuracy": 0.7525510191917419,
          "mae": 0.75,
          "gradient_norm": 0.0951381891965866,
          "learning_rate": 0.00064
        }
      ]
    }
  ]
}