{
  "config": {
    "dataset": "assist2015_dkvmn",
    "data_dir": "data",
    "device": "cuda",
    "epochs": 15,
    "batch_size": 64,
    "lr": 0.001,
    "patience": 10,
    "hidden_dim": 128,
    "num_layers": 2,
    "dropout": 0.1,
    "n_folds": 0,
    "fold": null,
    "hyperopt": false,
    "hyperopt_trials": 50,
    "hyperopt_metric": "quadratic_weighted_kappa",
    "output_dir": null,
    "save_model": true,
    "save_results": true,
    "verbose": false,
    "debug": false,
    "seed": 42,
    "resume": null,
    "validate_only": false,
    "save_freq": 5,
    "datasets": null,
    "all": false,
    "exclude": [],
    "parallel": false,
    "max_workers": 4,
    "model": "DEEP-GPCM",
    "models": null,
    "loss": "factory",
    "no_cv": false,
    "cv": false,
    "adaptive": true,
    "no_adaptive": false,
    "adaptive_epochs": "5,15,40",
    "adaptive_arch": true,
    "adaptive_learning": true
  },
  "metrics": {
    "epoch": 6,
    "train_loss": 0.4843673560648195,
    "train_accuracy": 0.7387925282306141,
    "gradient_norm": 0.0644956695877256,
    "learning_rate": 0.001,
    "categorical_accuracy": 0.7457256270189159,
    "ordinal_accuracy": 1.0,
    "quadratic_weighted_kappa": 0.07268428587451536,
    "mean_absolute_error": 0.2542743729810841,
    "kendall_tau": 0.1477904961528941,
    "spearman_correlation": 0.1477904961528941,
    "cohen_kappa": 0.07268428587451536,
    "cat_0_accuracy": 0.061965571557155714,
    "cat_1_accuracy": 0.989471678816015,
    "cat_0_precision": 0.6772210267445435,
    "cat_0_recall": 0.061965571557155714,
    "cat_0_f1": 0.11354206932096379,
    "cat_1_precision": 0.7474134666363705,
    "cat_1_recall": 0.989471678816015,
    "cat_1_f1": 0.8515755454973011,
    "cross_entropy": 0.5199988081401345,
    "best_epoch": 6,
    "total_epochs": 15,
    "parameters": 88857,
    "model_type": "DeepGPCM"
  },
  "training_history": [
    {
      "epoch": 1,
      "train_loss": 0.5161679998761223,
      "train_accuracy": 0.7293452539387951,
      "gradient_norm": 0.11390506821654496,
      "learning_rate": 0.001,
      "categorical_accuracy": 0.742480577751824,
      "ordinal_accuracy": 1.0,
      "quadratic_weighted_kappa": 0.04995130591115449,
      "mean_absolute_error": 0.25751942224817603,
      "kendall_tau": 0.11757800197521773,
      "spearman_correlation": 0.11757800197521773,
      "cohen_kappa": 0.04995130591115449,
      "cat_0_accuracy": 0.04317619261926193,
      "cat_1_accuracy": 0.9917678555313794,
      "cat_0_precision": 0.6515280135823429,
      "cat_0_recall": 0.04317619261926193,
      "cat_0_f1": 0.0809855439485069,
      "cat_1_precision": 0.7440926222663568,
      "cat_1_recall": 0.9917678555313794,
      "cat_1_f1": 0.8502608979704115,
      "cross_entropy": 0.5304839650134485
    },
    {
      "epoch": 2,
      "train_loss": 0.4899956057629278,
      "train_accuracy": 0.7372757138325452,
      "gradient_norm": 0.07482063002704133,
      "learning_rate": 0.001,
      "categorical_accuracy": 0.7422366446634093,
      "ordinal_accuracy": 1.0,
      "quadratic_weighted_kappa": 0.03823879868361402,
      "mean_absolute_error": 0.2577633553365907,
      "kendall_tau": 0.11165815922738559,
      "spearman_correlation": 0.1116581592273856,
      "cohen_kappa": 0.03823879868361424,
      "cat_0_accuracy": 0.030490549054905492,
      "cat_1_accuracy": 0.995959130059861,
      "cat_0_precision": 0.7289845326160054,
      "cat_0_recall": 0.030490549054905492,
      "cat_0_f1": 0.05853289775641891,
      "cat_1_precision": 0.7423839277706359,
      "cat_1_recall": 0.995959130059861,
      "cat_1_f1": 0.8506767954026729,
      "cross_entropy": 0.5252291554336908
    },
    {
      "epoch": 3,
      "train_loss": 0.4869689239609626,
      "train_accuracy": 0.7380250055604374,
      "gradient_norm": 0.0712655718558498,
      "learning_rate": 0.001,
      "categorical_accuracy": 0.742850173340331,
      "ordinal_accuracy": 1.0,
      "quadratic_weighted_kappa": 0.046751833650567454,
      "mean_absolute_error": 0.257149826659669,
      "kendall_tau": 0.11912103178785591,
      "spearman_correlation": 0.11912103178785591,
      "cohen_kappa": 0.046751833650567676,
      "cat_0_accuracy": 0.038675742574257425,
      "cat_1_accuracy": 0.9938735197681764,
      "cat_0_precision": 0.6923464249748238,
      "cat_0_recall": 0.038675742574257425,
      "cat_0_f1": 0.07325909744791945,
      "cat_1_precision": 0.7436026317171429,
      "cat_1_recall": 0.9938735197681764,
      "cat_1_f1": 0.8507132190123076,
      "cross_entropy": 0.5235211849543194
    },
    {
      "epoch": 4,
      "train_loss": 0.4858615620722694,
      "train_accuracy": 0.738300292788933,
      "gradient_norm": 0.0703749572708001,
      "learning_rate": 0.001,
      "categorical_accuracy": 0.7447055431946364,
      "ordinal_accuracy": 1.0,
      "quadratic_weighted_kappa": 0.05960748431184526,
      "mean_absolute_error": 0.25529445680536356,
      "kendall_tau": 0.13716479037954601,
      "spearman_correlation": 0.13716479037954601,
      "cohen_kappa": 0.05960748431184526,
      "cat_0_accuracy": 0.04908303330333033,
      "cat_1_accuracy": 0.9926803100339915,
      "cat_0_precision": 0.705050505050505,
      "cat_0_recall": 0.04908303330333033,
      "cat_0_f1": 0.09177689536382044,
      "cat_1_precision": 0.7454445515330401,
      "cat_1_recall": 0.9926803100339915,
      "cat_1_f1": 0.851478676695092,
      "cross_entropy": 0.5227080554797076
    },
    {
      "epoch": 5,
      "train_loss": 0.4850401968484925,
      "train_accuracy": 0.7388508672459245,
      "gradient_norm": 0.06593976916384793,
      "learning_rate": 0.001,
      "categorical_accuracy": 0.7436928512821271,
      "ordinal_accuracy": 1.0,
      "quadratic_weighted_kappa": 0.05118303857764106,
      "mean_absolute_error": 0.2563071487178729,
      "kendall_tau": 0.1272903306471109,
      "spearman_correlation": 0.12729033064711087,
      "cohen_kappa": 0.05118303857764106,
      "cat_0_accuracy": 0.04176980198019802,
      "cat_1_accuracy": 0.9939136276584011,
      "cat_0_precision": 0.7098470363288719,
      "cat_0_recall": 0.04176980198019802,
      "cat_0_f1": 0.07889703538412496,
      "cat_1_precision": 0.7442244596106343,
      "cat_1_recall": 0.9939136276584011,
      "cat_1_f1": 0.851134714625497,
      "cross_entropy": 0.5216008112188241
    },
    {
      "epoch": 6,
      "train_loss": 0.4843673560648195,
      "train_accuracy": 0.7387925282306141,
      "gradient_norm": 0.0644956695877256,
      "learning_rate": 0.001,
      "categorical_accuracy": 0.7457256270189159,
      "ordinal_accuracy": 1.0,
      "quadratic_weighted_kappa": 0.07268428587451536,
      "mean_absolute_error": 0.2542743729810841,
      "kendall_tau": 0.1477904961528941,
      "spearman_correlation": 0.1477904961528941,
      "cohen_kappa": 0.07268428587451536,
      "cat_0_accuracy": 0.061965571557155714,
      "cat_1_accuracy": 0.989471678816015,
      "cat_0_precision": 0.6772210267445435,
      "cat_0_recall": 0.061965571557155714,
      "cat_0_f1": 0.11354206932096379,
      "cat_1_precision": 0.7474134666363705,
      "cat_1_recall": 0.989471678816015,
      "cat_1_f1": 0.8515755454973011,
      "cross_entropy": 0.5199988081401345
    },
    {
      "epoch": 7,
      "train_loss": 0.4837434242569631,
      "train_accuracy": 0.7391407392282477,
      "gradient_norm": 0.06410160449694001,
      "learning_rate": 0.001,
      "categorical_accuracy": 0.7452303689303165,
      "ordinal_accuracy": 1.0,
      "quadratic_weighted_kappa": 0.06368148715683108,
      "mean_absolute_error": 0.25476963106968353,
      "kendall_tau": 0.1419833153106483,
      "spearman_correlation": 0.14198331531064834,
      "cohen_kappa": 0.06368148715683108,
      "cat_0_accuracy": 0.05257088208820882,
      "cat_1_accuracy": 0.9921488804885141,
      "cat_0_precision": 0.7047511312217195,
      "cat_0_recall": 0.05257088208820882,
      "cat_0_f1": 0.09784315778452518,
      "cat_1_precision": 0.7460397644592893,
      "cat_1_recall": 0.9921488804885141,
      "cat_1_f1": 0.8516710994052383,
      "cross_entropy": 0.5201271379256426
    },
    {
      "epoch": 8,
      "train_loss": 0.4827400432719338,
      "train_accuracy": 0.7391790242070452,
      "gradient_norm": 0.06756777697122626,
      "learning_rate": 0.001,
      "categorical_accuracy": 0.7444911777533023,
      "ordinal_accuracy": 1.0,
      "quadratic_weighted_kappa": 0.05702728864263984,
      "mean_absolute_error": 0.2555088222466977,
      "kendall_tau": 0.13497552440882246,
      "spearman_correlation": 0.13497552440882246,
      "cohen_kappa": 0.05702728864263984,
      "cat_0_accuracy": 0.04660778577857786,
      "cat_1_accuracy": 0.9932719014148058,
      "cat_0_precision": 0.7117697594501718,
      "cat_0_recall": 0.04660778577857786,
      "cat_0_f1": 0.08748680042238649,
      "cat_1_precision": 0.7450641194389079,
      "cat_1_recall": 0.9932719014148058,
      "cat_1_f1": 0.8514478739588974,
      "cross_entropy": 0.519627498107428
    },
    {
      "epoch": 9,
      "train_loss": 0.4826713491591715,
      "train_accuracy": 0.7393759183837176,
      "gradient_norm": 0.0630327352142382,
      "learning_rate": 0.001,
      "categorical_accuracy": 0.7440476630470939,
      "ordinal_accuracy": 1.0,
      "quadratic_weighted_kappa": 0.055610467770283,
      "mean_absolute_error": 0.25595233695290615,
      "kendall_tau": 0.13115561607608278,
      "spearman_correlation": 0.13115561607608278,
      "cohen_kappa": 0.055610467770283,
      "cat_0_accuracy": 0.04601710171017102,
      "cat_1_accuracy": 0.992880849485115,
      "cat_0_precision": 0.6973572037510657,
      "cat_0_recall": 0.04601710171017102,
      "cat_0_f1": 0.08633700986859465,
      "cat_1_precision": 0.7448716309229184,
      "cat_1_recall": 0.992880849485115,
      "cat_1_f1": 0.8511785032750528,
      "cross_entropy": 0.5196008043881799
    },
    {
      "epoch": 10,
      "train_loss": 0.4820122214094285,
      "train_accuracy": 0.7393558643472047,
      "gradient_norm": 0.06437304685072552,
      "learning_rate": 0.0008,
      "categorical_accuracy": 0.7456960593718354,
      "ordinal_accuracy": 1.0,
      "quadratic_weighted_kappa": 0.06835867918216232,
      "mean_absolute_error": 0.25430394062816464,
      "kendall_tau": 0.14637452636841364,
      "spearman_correlation": 0.1463745263684136,
      "cohen_kappa": 0.06835867918216243,
      "cat_0_accuracy": 0.05693069306930693,
      "cat_1_accuracy": 0.9912263990133459,
      "cat_0_precision": 0.6981717833735771,
      "cat_0_recall": 0.05693069306930693,
      "cat_0_f1": 0.10527684585576448,
      "cat_1_precision": 0.7467367657722987,
      "cat_1_recall": 0.9912263990133459,
      "cat_1_f1": 0.8517846756995455,
      "cross_entropy": 0.5183438335447339
    },
    {
      "epoch": 11,
      "train_loss": 0.4810895130278603,
      "train_accuracy": 0.7396402670468426,
      "gradient_norm": 0.06931558234857456,
      "learning_rate": 0.0008,
      "categorical_accuracy": 0.7449494762830511,
      "ordinal_accuracy": 1.0,
      "quadratic_weighted_kappa": 0.06371104141875306,
      "mean_absolute_error": 0.2550505237169489,
      "kendall_tau": 0.13995444364469237,
      "spearman_correlation": 0.13995444364469234,
      "cohen_kappa": 0.06371104141875306,
      "cat_0_accuracy": 0.053274077407740775,
      "cat_1_accuracy": 0.991517181217475,
      "cat_0_precision": 0.6912408759124088,
      "cat_0_recall": 0.053274077407740775,
      "cat_0_f1": 0.09892405724433302,
      "cat_1_precision": 0.7460597692824216,
      "cat_1_recall": 0.991517181217475,
      "cat_1_f1": 0.8514513032022525,
      "cross_entropy": 0.5186725966575082
    },
    {
      "epoch": 12,
      "train_loss": 0.48095508760982947,
      "train_accuracy": 0.7397587681716917,
      "gradient_norm": 0.063931284186941,
      "learning_rate": 0.0008,
      "categorical_accuracy": 0.7444098667238308,
      "ordinal_accuracy": 1.0,
      "quadratic_weighted_kappa": 0.05644634199083609,
      "mean_absolute_error": 0.2555901332761692,
      "kendall_tau": 0.13421383037470158,
      "spearman_correlation": 0.1342138303747016,
      "cohen_kappa": 0.0564463419908362,
      "cat_0_accuracy": 0.046129612961296126,
      "cat_1_accuracy": 0.9933320632501429,
      "cat_0_precision": 0.7114967462039046,
      "cat_0_recall": 0.046129612961296126,
      "cat_0_f1": 0.08664183638428824,
      "cat_1_precision": 0.7449803726932275,
      "cat_1_recall": 0.9933320632501429,
      "cat_1_f1": 0.8514152869033857,
      "cross_entropy": 0.5183388036290075
    },
    {
      "epoch": 13,
      "train_loss": 0.4807283643993639,
      "train_accuracy": 0.7398718000138556,
      "gradient_norm": 0.06875077680113816,
      "learning_rate": 0.0008,
      "categorical_accuracy": 0.7432493365759186,
      "ordinal_accuracy": 1.0,
      "quadratic_weighted_kappa": 0.04679414429232831,
      "mean_absolute_error": 0.25675066342408137,
      "kendall_tau": 0.12263257689803751,
      "spearman_correlation": 0.12263257689803753,
      "cohen_kappa": 0.04679414429232831,
      "cat_0_accuracy": 0.037803780378037805,
      "cat_1_accuracy": 0.9947258124354513,
      "cat_0_precision": 0.718716577540107,
      "cat_0_recall": 0.037803780378037805,
      "cat_0_f1": 0.0718294051627385,
      "cat_1_precision": 0.7435932030611709,
      "cat_1_recall": 0.9947258124354513,
      "cat_1_f1": 0.8510191126514086,
      "cross_entropy": 0.5193261802682804
    },
    {
      "epoch": 14,
      "train_loss": 0.4805756778486313,
      "train_accuracy": 0.7397532988890064,
      "gradient_norm": 0.06601113211663981,
      "learning_rate": 0.00064,
      "categorical_accuracy": 0.7455925726070534,
      "ordinal_accuracy": 1.0,
      "quadratic_weighted_kappa": 0.06738048716583112,
      "mean_absolute_error": 0.25440742739294664,
      "kendall_tau": 0.14541955526823144,
      "spearman_correlation": 0.14541955526823144,
      "cohen_kappa": 0.06738048716583112,
      "cat_0_accuracy": 0.05603060306030603,
      "cat_1_accuracy": 0.9914068845193571,
      "cat_0_precision": 0.6991926991926992,
      "cat_0_recall": 0.05603060306030603,
      "cat_0_f1": 0.10374729824744147,
      "cat_1_precision": 0.7465907546400471,
      "cat_1_recall": 0.9914068845193571,
      "cat_1_f1": 0.8517562940150324,
      "cross_entropy": 0.5181165121866629
    },
    {
      "epoch": 15,
      "train_loss": 0.48013652464555157,
      "train_accuracy": 0.7399939473271615,
      "gradient_norm": 0.0641280452630693,
      "learning_rate": 0.00064,
      "categorical_accuracy": 0.7456295321659041,
      "ordinal_accuracy": 1.0,
      "quadratic_weighted_kappa": 0.06700023491946161,
      "mean_absolute_error": 0.25437046783409595,
      "kendall_tau": 0.14559845076078265,
      "spearman_correlation": 0.14559845076078265,
      "cohen_kappa": 0.06700023491946161,
      "cat_0_accuracy": 0.055496174617461744,
      "cat_1_accuracy": 0.9916475318607053,
      "cat_0_precision": 0.703136136849608,
      "cat_0_recall": 0.055496174617461744,
      "cat_0_f1": 0.10287293393816153,
      "cat_1_precision": 0.746529586267805,
      "cat_1_recall": 0.9916475318607053,
      "cat_1_f1": 0.8518052780265969,
      "cross_entropy": 0.5177079119820363
    }
  ],
  "timestamp": "2025-08-19T16:16:47.049792"
}